filestat_pkg/__init__.py
filestat_pkg/filest.py
filestat_pkg-0.0.5.data/scripts/filest.py
filestat_pkg-0.0.5.dist-info/METADATA
filestat_pkg-0.0.5.dist-info/WHEEL
filestat_pkg-0.0.5.dist-info/entry_points.txt
filestat_pkg-0.0.5.dist-info/top_level.txt
filestat_pkg-0.0.5.dist-info/RECORD
